ntinput/__init__.py
ntinput/misc.py
ntinput/pkgg/__init__.py
ntinput-1.1.0.dist-info/METADATA
ntinput-1.1.0.dist-info/WHEEL
ntinput-1.1.0.dist-info/RECORD
