Metadata-Version: 2.1
Name: ntinput
Version: 1.1.0
Summary: Simple library to manipulate mouse and keyboard using shadowed syscall functions
Author: Xenely
Author-email: amaryatkin@vk.com
Requires-Python: >=3.10,<4.0
Classifier: Programming Language :: Python :: 3
Classifier: Programming Language :: Python :: 3.10
Classifier: Programming Language :: Python :: 3.11
Classifier: Programming Language :: Python :: 3.12
